dede/__init__.py
dede/problem.py
dede/subproblem.py
dede/subproblems_wrap.py
dede/utils.py
dede-0.1.6.dist-info/licenses/LICENSE
dede-0.1.6.dist-info/METADATA
dede-0.1.6.dist-info/WHEEL
dede-0.1.6.dist-info/top_level.txt
dede-0.1.6.dist-info/RECORD
