Metadata-Version: 2.4
Name: dede
Version: 0.1.6
Summary: Decouple and Decompose: Scaling Resource Allocation through a Different Lens
Home-page: https://github.com/illinois-nsai/dede
Author: Zhiying Xu
Author-email: xuzhiying9510@gmail.com
Classifier: Programming Language :: Python :: 3
Classifier: License :: OSI Approved :: MIT License
Classifier: Operating System :: OS Independent
Requires-Python: >=3.8
License-File: LICENSE
Requires-Dist: cvxpy==1.4.0
Requires-Dist: numpy==1.26.4
Requires-Dist: ray
Dynamic: author
Dynamic: author-email
Dynamic: classifier
Dynamic: description
Dynamic: description-content-type
Dynamic: home-page
Dynamic: license-file
Dynamic: requires-dist
Dynamic: requires-python
Dynamic: summary
